{"index":526,"name":"gigalith","stats":{"HP":85,"ATK":135,"DEF":130,"SPATK":60,"SPDEF":80,"SPD":25},"type":["rock"],"abilities":[{"ability":"sturdy","is_hidden":false},{"ability":"sand-stream","is_hidden":false},{"ability":"sand-force","is_hidden":true}],"moves":[{"name":"sand-attack","power":null,"accuracy":100,"pp":15,"type":"ground","class":"status"},{"name":"headbutt","power":70,"accuracy":100,"pp":15,"type":"normal","class":"physical"},{"name":"tackle","power":40,"accuracy":100,"pp":35,"type":"normal","class":"physical"},{"name":"hyper-beam","power":150,"accuracy":90,"pp":5,"type":"normal","class":"special"},{"name":"strength","power":80,"accuracy":100,"pp":15,"type":"normal","class":"physical"},{"name":"solar-beam","power":120,"accuracy":100,"pp":10,"type":"grass","class":"special"},{"name":"earthquake","power":100,"accuracy":100,"pp":10,"type":"ground","class":"physical"},{"name":"toxic","power":null,"accuracy":90,"pp":10,"type":"poison","class":"status"},{"name":"double-team","power":null,"accuracy":null,"pp":15,"type":"normal","class":"status"},{"name":"harden","power":null,"accuracy":null,"pp":30,"type":"normal","class":"status"},{"name":"explosion","power":250,"accuracy":100,"pp":5,"type":"normal","class":"physical"},{"name":"rest","power":null,"accuracy":null,"pp":10,"type":"psychic","class":"status"},{"name":"rock-slide","power":75,"accuracy":90,"pp":10,"type":"rock","class":"physical"},{"name":"substitute","power":null,"accuracy":null,"pp":10,"type":"normal","class":"status"},{"name":"snore","power":50,"accuracy":100,"pp":15,"type":"normal","class":"special"},{"name":"protect","power":null,"accuracy":null,"pp":10,"type":"normal","class":"status"},{"name":"mud-slap","power":20,"accuracy":100,"pp":10,"type":"ground","class":"special"},{"name":"sandstorm","power":null,"accuracy":null,"pp":10,"type":"rock","class":"status"},{"name":"swagger","power":null,"accuracy":85,"pp":15,"type":"normal","class":"status"},{"name":"attract","power":null,"accuracy":100,"pp":15,"type":"normal","class":"status"},{"name":"sleep-talk","power":null,"accuracy":null,"pp":10,"type":"normal","class":"status"},{"name":"return","power":null,"accuracy":100,"pp":20,"type":"normal","class":"physical"},{"name":"frustration","power":null,"accuracy":100,"pp":20,"type":"normal","class":"physical"},{"name":"hidden-power","power":60,"accuracy":100,"pp":15,"type":"normal","class":"special"},{"name":"rock-smash","power":40,"accuracy":100,"pp":15,"type":"fighting","class":"physical"},{"name":"facade","power":70,"accuracy":100,"pp":20,"type":"normal","class":"physical"},{"name":"nature-power","power":null,"accuracy":null,"pp":20,"type":"normal","class":"status"},{"name":"superpower","power":120,"accuracy":100,"pp":5,"type":"fighting","class":"physical"},{"name":"secret-power","power":70,"accuracy":100,"pp":20,"type":"normal","class":"physical"},{"name":"rock-tomb","power":60,"accuracy":95,"pp":15,"type":"rock","class":"physical"},{"name":"iron-defense","power":null,"accuracy":null,"pp":15,"type":"steel","class":"status"},{"name":"block","power":null,"accuracy":null,"pp":5,"type":"normal","class":"status"},{"name":"rock-blast","power":25,"accuracy":90,"pp":10,"type":"rock","class":"physical"},{"name":"gravity","power":null,"accuracy":null,"pp":5,"type":"psychic","class":"status"},{"name":"rock-polish","power":null,"accuracy":null,"pp":20,"type":"rock","class":"status"},{"name":"power-gem","power":80,"accuracy":100,"pp":20,"type":"rock","class":"special"},{"name":"earth-power","power":90,"accuracy":100,"pp":10,"type":"ground","class":"special"},{"name":"giga-impact","power":150,"accuracy":90,"pp":5,"type":"normal","class":"physical"},{"name":"flash-cannon","power":80,"accuracy":100,"pp":10,"type":"steel","class":"special"},{"name":"iron-head","power":80,"accuracy":100,"pp":15,"type":"steel","class":"physical"},{"name":"stone-edge","power":100,"accuracy":80,"pp":5,"type":"rock","class":"physical"},{"name":"stealth-rock","power":null,"accuracy":null,"pp":20,"type":"rock","class":"status"},{"name":"smack-down","power":50,"accuracy":100,"pp":15,"type":"rock","class":"physical"},{"name":"round","power":60,"accuracy":100,"pp":15,"type":"normal","class":"special"},{"name":"bulldoze","power":60,"accuracy":100,"pp":20,"type":"ground","class":"physical"},{"name":"confide","power":null,"accuracy":null,"pp":20,"type":"normal","class":"status"}],"evolutions: ":["roggenrola","boldore","gigalith"]}