{"index":636,"name":"larvesta","stats":{"HP":55,"ATK":85,"DEF":55,"SPATK":50,"SPDEF":55,"SPD":60},"type":["bug","fire"],"abilities":[{"ability":"flame-body","is_hidden":false},{"ability":"swarm","is_hidden":true}],"moves":[{"name":"take-down","power":90,"accuracy":85,"pp":20,"type":"normal","class":"physical"},{"name":"thrash","power":120,"accuracy":100,"pp":10,"type":"normal","class":"physical"},{"name":"double-edge","power":120,"accuracy":100,"pp":15,"type":"normal","class":"physical"},{"name":"ember","power":40,"accuracy":100,"pp":25,"type":"fire","class":"special"},{"name":"flamethrower","power":90,"accuracy":100,"pp":15,"type":"fire","class":"special"},{"name":"absorb","power":20,"accuracy":100,"pp":25,"type":"grass","class":"special"},{"name":"solar-beam","power":120,"accuracy":100,"pp":10,"type":"grass","class":"special"},{"name":"string-shot","power":null,"accuracy":95,"pp":40,"type":"bug","class":"status"},{"name":"toxic","power":null,"accuracy":90,"pp":10,"type":"poison","class":"status"},{"name":"psychic","power":90,"accuracy":100,"pp":10,"type":"psychic","class":"special"},{"name":"double-team","power":null,"accuracy":null,"pp":15,"type":"normal","class":"status"},{"name":"harden","power":null,"accuracy":null,"pp":30,"type":"normal","class":"status"},{"name":"light-screen","power":null,"accuracy":null,"pp":30,"type":"psychic","class":"status"},{"name":"fire-blast","power":110,"accuracy":85,"pp":5,"type":"fire","class":"special"},{"name":"amnesia","power":null,"accuracy":null,"pp":20,"type":"psychic","class":"status"},{"name":"leech-life","power":80,"accuracy":100,"pp":10,"type":"bug","class":"physical"},{"name":"rest","power":null,"accuracy":null,"pp":10,"type":"psychic","class":"status"},{"name":"substitute","power":null,"accuracy":null,"pp":10,"type":"normal","class":"status"},{"name":"flame-wheel","power":60,"accuracy":100,"pp":25,"type":"fire","class":"physical"},{"name":"snore","power":50,"accuracy":100,"pp":15,"type":"normal","class":"special"},{"name":"protect","power":null,"accuracy":null,"pp":10,"type":"normal","class":"status"},{"name":"foresight","power":null,"accuracy":null,"pp":40,"type":"normal","class":"status"},{"name":"giga-drain","power":75,"accuracy":100,"pp":10,"type":"grass","class":"special"},{"name":"endure","power":null,"accuracy":null,"pp":10,"type":"normal","class":"status"},{"name":"swagger","power":null,"accuracy":85,"pp":15,"type":"normal","class":"status"},{"name":"sleep-talk","power":null,"accuracy":null,"pp":10,"type":"normal","class":"status"},{"name":"return","power":null,"accuracy":100,"pp":20,"type":"normal","class":"physical"},{"name":"frustration","power":null,"accuracy":100,"pp":20,"type":"normal","class":"physical"},{"name":"safeguard","power":null,"accuracy":null,"pp":25,"type":"normal","class":"status"},{"name":"morning-sun","power":null,"accuracy":null,"pp":5,"type":"normal","class":"status"},{"name":"hidden-power","power":60,"accuracy":100,"pp":15,"type":"normal","class":"special"},{"name":"sunny-day","power":null,"accuracy":null,"pp":5,"type":"fire","class":"status"},{"name":"heat-wave","power":95,"accuracy":90,"pp":10,"type":"fire","class":"special"},{"name":"will-o-wisp","power":null,"accuracy":85,"pp":15,"type":"fire","class":"status"},{"name":"facade","power":70,"accuracy":100,"pp":20,"type":"normal","class":"physical"},{"name":"secret-power","power":70,"accuracy":100,"pp":20,"type":"normal","class":"physical"},{"name":"overheat","power":130,"accuracy":90,"pp":5,"type":"fire","class":"special"},{"name":"signal-beam","power":75,"accuracy":100,"pp":15,"type":"bug","class":"special"},{"name":"calm-mind","power":null,"accuracy":null,"pp":20,"type":"psychic","class":"status"},{"name":"u-turn","power":70,"accuracy":100,"pp":20,"type":"bug","class":"physical"},{"name":"magnet-rise","power":null,"accuracy":null,"pp":10,"type":"electric","class":"status"},{"name":"flare-blitz","power":120,"accuracy":100,"pp":15,"type":"fire","class":"physical"},{"name":"bug-buzz","power":90,"accuracy":100,"pp":10,"type":"bug","class":"special"},{"name":"zen-headbutt","power":80,"accuracy":90,"pp":15,"type":"psychic","class":"physical"},{"name":"bug-bite","power":60,"accuracy":100,"pp":20,"type":"bug","class":"physical"},{"name":"flame-charge","power":50,"accuracy":100,"pp":20,"type":"fire","class":"physical"},{"name":"round","power":60,"accuracy":100,"pp":15,"type":"normal","class":"special"},{"name":"incinerate","power":60,"accuracy":100,"pp":15,"type":"fire","class":"special"},{"name":"acrobatics","power":55,"accuracy":100,"pp":15,"type":"flying","class":"physical"},{"name":"struggle-bug","power":50,"accuracy":100,"pp":20,"type":"bug","class":"special"},{"name":"wild-charge","power":90,"accuracy":100,"pp":15,"type":"electric","class":"physical"},{"name":"confide","power":null,"accuracy":null,"pp":20,"type":"normal","class":"status"}],"evolutions: ":["larvesta","volcarona"]}